azure/purview/catalog/__init__.py
azure/purview/catalog/_client.py
azure/purview/catalog/_configuration.py
azure/purview/catalog/_patch.py
azure/purview/catalog/_vendor.py
azure/purview/catalog/_version.py
azure/purview/catalog/py.typed
azure/purview/catalog/aio/__init__.py
azure/purview/catalog/aio/_client.py
azure/purview/catalog/aio/_configuration.py
azure/purview/catalog/aio/_patch.py
azure/purview/catalog/aio/operations/__init__.py
azure/purview/catalog/aio/operations/_operations.py
azure/purview/catalog/aio/operations/_patch.py
azure/purview/catalog/operations/__init__.py
azure/purview/catalog/operations/_operations.py
azure/purview/catalog/operations/_patch.py
azure_purview_catalog-1.0.0b4.dist-info/LICENSE
azure_purview_catalog-1.0.0b4.dist-info/METADATA
azure_purview_catalog-1.0.0b4.dist-info/WHEEL
azure_purview_catalog-1.0.0b4.dist-info/top_level.txt
azure_purview_catalog-1.0.0b4.dist-info/RECORD
